[{
  "name": "Salmon",
  "category_id": {
    "$oid": "68c018a1699aa89005b47e1c"
  },
  "allergen_tags": "[\"fish\"]",
  "translations": {
    "name": {
      "en": "Salmon",
      "fi": "Lohi",
      "sv": "Lax"
    }
  },
  "created_at": {
    "$date": "2025-09-09T12:08:01.955Z"
  },
  "updated_at": {
    "$date": "2025-09-09T12:08:01.955Z"
  }
},
{
  "name": "Greek Yogurt",
  "category_id": {
    "$oid": "68c018a1699aa89005b47e1e"
  },
  "allergen_tags": "[\"dairy\"]",
  "translations": {
    "name": {
      "en": "Greek Yogurt",
      "fi": "Kreikkalainen jogurtti",
      "sv": "Grekisk yoghurt"
    }
  },
  "created_at": {
    "$date": "2025-09-09T12:08:01.955Z"
  },
  "updated_at": {
    "$date": "2025-09-09T12:08:01.955Z"
  }
},
{
  "name": "Mozzarella",
  "category_id": {
    "$oid": "68c018a1699aa89005b47e1e"
  },
  "allergen_tags": "[\"dairy\"]",
  "translations": {
    "name": {
      "en": "Mozzarella",
      "fi": "Mozzarella",
      "sv": "Mozzarella"
    }
  },
  "created_at": {
    "$date": "2025-09-09T12:08:01.955Z"
  },
  "updated_at": {
    "$date": "2025-09-09T12:08:01.955Z"
  }
},
{
  "name": "Spinach",
  "category_id": {
    "$oid": "68c018a1699aa89005b47e20"
  },
  "allergen_tags": "[]",
  "translations": {
    "name": {
      "en": "Spinach",
      "fi": "Pinaatti",
      "sv": "Spenat"
    }
  },
  "created_at": {
    "$date": "2025-09-09T12:08:01.955Z"
  },
  "updated_at": {
    "$date": "2025-09-09T12:08:01.955Z"
  }
},
{
  "name": "Almonds",
  "category_id": {
    "$oid": "68c018a1699aa89005b47e1d"
  },
  "allergen_tags": "[\"nuts\"]",
  "translations": {
    "name": {
      "en": "Almonds",
      "fi": "Mantelit",
      "sv": "Mandlar"
    }
  },
  "created_at": {
    "$date": "2025-09-09T12:08:01.955Z"
  },
  "updated_at": {
    "$date": "2025-09-09T12:08:01.955Z"
  }
},
{
  "name": "Chicken Breast",
  "category_id": {
    "$oid": "68c018a1699aa89005b47e1c"
  },
  "allergen_tags": "[]",
  "translations": {
    "name": {
      "en": "Chicken Breast",
      "fi": "Kananrinta",
      "sv": "Kycklingbröst"
    }
  },
  "created_at": {
    "$date": "2025-09-09T12:08:01.955Z"
  },
  "updated_at": {
    "$date": "2025-09-09T12:08:01.955Z"
  }
},
{
  "name": "Blueberries",
  "category_id": {
    "$oid": "68c018a1699aa89005b47e21"
  },
  "allergen_tags": "[]",
  "translations": {
    "name": {
      "en": "Blueberries",
      "fi": "Mustikat",
      "sv": "Blåbär"
    }
  },
  "created_at": {
    "$date": "2025-09-09T12:08:01.955Z"
  },
  "updated_at": {
    "$date": "2025-09-09T12:08:01.955Z"
  }
},
{
  "name": "Cherry Tomatoes",
  "category_id": {
    "$oid": "68c018a1699aa89005b47e20"
  },
  "allergen_tags": "[]",
  "translations": {
    "name": {
      "en": "Cherry Tomatoes",
      "fi": "Kirsikkatomaatit",
      "sv": "Körsbärstomater"
    }
  },
  "created_at": {
    "$date": "2025-09-09T12:08:01.955Z"
  },
  "updated_at": {
    "$date": "2025-09-09T12:08:01.955Z"
  }
},
{
  "name": "Avocado",
  "category_id": {
    "$oid": "68c018a1699aa89005b47e21"
  },
  "allergen_tags": "[]",
  "translations": {
    "name": {
      "en": "Avocado",
      "fi": "Avokado",
      "sv": "Avokado"
    }
  },
  "created_at": {
    "$date": "2025-09-09T12:08:01.955Z"
  },
  "updated_at": {
    "$date": "2025-09-09T12:08:01.955Z"
  }
},
{
  "name": "Walnuts",
  "category_id": {
    "$oid": "68c018a1699aa89005b47e1d"
  },
  "allergen_tags": "[\"nuts\"]",
  "translations": {
    "name": {
      "en": "Walnuts",
      "fi": "Saksanpähkinät",
      "sv": "Valnötter"
    }
  },
  "created_at": {
    "$date": "2025-09-09T12:08:01.955Z"
  },
  "updated_at": {
    "$date": "2025-09-09T12:08:01.955Z"
  }
},
{
  "name": "Basil",
  "category_id": {
    "$oid": "68c018a1699aa89005b47e1f"
  },
  "allergen_tags": "[]",
  "translations": {
    "name": {
      "en": "Basil",
      "fi": "Basilika",
      "sv": "Basilika"
    }
  },
  "created_at": {
    "$date": "2025-09-09T12:08:01.955Z"
  },
  "updated_at": {
    "$date": "2025-09-09T12:08:01.955Z"
  }
},
{
  "name": "Quinoa",
  "category_id": {
    "$oid": "68c018a1699aa89005b47e22"
  },
  "allergen_tags": "[]",
  "translations": {
    "name": {
      "en": "Quinoa",
      "fi": "Kvinoa",
      "sv": "Quinoa"
    }
  },
  "created_at": {
    "$date": "2025-09-09T12:08:01.955Z"
  },
  "updated_at": {
    "$date": "2025-09-09T12:08:01.955Z"
  }
},
{
  "name": "Red Bell Pepper",
  "category_id": {
    "$oid": "68c018a1699aa89005b47e20"
  },
  "allergen_tags": "[]",
  "translations": {
    "name": {
      "en": "Red Bell Pepper",
      "fi": "Punainen paprika",
      "sv": "Röd paprika"
    }
  },
  "created_at": {
    "$date": "2025-09-09T12:08:01.955Z"
  },
  "updated_at": {
    "$date": "2025-09-09T12:08:01.955Z"
  }
},
{
  "name": "Whole Wheat Pasta",
  "category_id": {
    "$oid": "68c018a1699aa89005b47e22"
  },
  "allergen_tags": "[\"gluten\"]",
  "translations": {
    "name": {
      "en": "Whole Wheat Pasta",
      "fi": "Täysjyväpasta",
      "sv": "Fullkornspasta"
    }
  },
  "created_at": {
    "$date": "2025-09-09T12:08:01.955Z"
  },
  "updated_at": {
    "$date": "2025-09-09T12:08:01.955Z"
  }
},
{
  "name": "Ground Beef",
  "category_id": {
    "$oid": "68c018a1699aa89005b47e1c"
  },
  "allergen_tags": "[]",
  "translations": {
    "name": {
      "en": "Ground Beef",
      "fi": "Jauheliha",
      "sv": "Köttfärs"
    }
  },
  "created_at": {
    "$date": "2025-09-09T12:08:01.955Z"
  },
  "updated_at": {
    "$date": "2025-09-09T12:08:01.955Z"
  }
},
{
  "name": "Black Pepper",
  "category_id": {
    "$oid": "68c018a1699aa89005b47e1f"
  },
  "allergen_tags": "[]",
  "translations": {
    "name": {
      "en": "Black Pepper",
      "fi": "Mustapippuri",
      "sv": "Svartpeppar"
    }
  },
  "created_at": {
    "$date": "2025-09-09T12:08:01.955Z"
  },
  "updated_at": {
    "$date": "2025-09-09T12:08:01.955Z"
  }
},
{
  "name": "Tomato Sauce",
  "allergen_tags": "[]",
  "is_active": true,
  "restaurant_id": {
    "$oid": "68e79f43b7afb57d706ea5f00"
  },
  "category_id": {
    "$oid": "68e79f43b7afb57d706ea5f4"
  },
  "translations": {
    "name": {
      "en": "Tomato Sauce",
      "fi": "Tomaattikastike",
      "sv": "Tomatsås"
    }
  },
  "created_at": {
    "$date": "2025-10-09T11:40:51.995Z"
  },
  "updated_at": {
    "$date": "2025-10-09T11:40:51.995Z"
  }
},
{
  "name": "Mozzarella Cheese",
  "allergen_tags": "[\"dairy\"]",
  "is_active": true,
  "restaurant_id": {
    "$oid": "68e79f43b7afb57d706ea5f00"
  },
  "category_id": {
    "$oid": "68e79f43b7afb57d706ea5f4"
  },
  "translations": {
    "name": {
      "en": "Mozzarella Cheese",
      "fi": "Mozzarellajuusto",
      "sv": "Mozzarella ost"
    }
  },
  "created_at": {
    "$date": "2025-10-09T11:40:51.995Z"
  },
  "updated_at": {
    "$date": "2025-10-09T11:40:51.995Z"
  }
},
{
  "name": "Flour",
  "allergen_tags": "[\"gluten\"]",
  "is_active": true,
  "restaurant_id": {
    "$oid": "68e79f43b7afb57d706ea5f00"
  },
  "category_id": {
    "$oid": "68c018a1699aa89005b47e22"
  },
  "translations": {
    "name": {
      "en": "Flour",
      "fi": "Jauho",
      "sv": "Mjöl"
    }
  },
  "created_at": {
    "$date": "2025-10-09T11:40:51.995Z"
  },
  "updated_at": {
    "$date": "2025-10-09T11:40:51.995Z"
  }
},
{
  "name": "Yeast",
  "allergen_tags": "[]",
  "is_active": true,
  "restaurant_id": {
    "$oid": "68e79f43b7afb57d706ea5f00"
  },
  "category_id": {
    "$oid": "68c018a1699aa89005b47e1f"
  },
  "translations": {
    "name": {
      "en": "Yeast",
      "fi": "Hiiva",
      "sv": "Jäst"
    }
  },
  "created_at": {
    "$date": "2025-10-09T11:40:51.995Z"
  },
  "updated_at": {
    "$date": "2025-10-09T11:40:51.995Z"
  }
},
{
  "name": "Sunflower Oil",
  "allergen_tags": "[]",
  "is_active": true,
  "restaurant_id": {
    "$oid": "68e79f43b7afb57d706ea5f00"
  },
  "category_id": {
    "$oid": "68c018a1699aa89005b47e1f"
  },
  "translations": {
    "name": {
      "en": "Sunflower Oil",
      "fi": "Auringonkukkaöljy",
      "sv": "Solrosolja"
    }
  },
  "created_at": {
    "$date": "2025-10-09T11:40:51.995Z"
  },
  "updated_at": {
    "$date": "2025-10-09T11:40:51.995Z"
  }
},
{
  "name": "Salt",
  "allergen_tags": "[]",
  "is_active": true,
  "restaurant_id": {
    "$oid": "68e79f43b7afb57d706ea5f00"
  },
  "category_id": {
    "$oid": "68c018a1699aa89005b47e1f"
  },
  "translations": {
    "name": {
      "en": "Salt",
      "fi": "Suola",
      "sv": "Salt"
    }
  },
  "created_at": {
    "$date": "2025-10-09T11:40:51.995Z"
  },
  "updated_at": {
    "$date": "2025-10-09T11:40:51.995Z"
  }
},
{
  "name": "Fresh Basil",
  "allergen_tags": "[]",
  "is_active": true,
  "restaurant_id": {
    "$oid": "68e79f43b7afb57d706ea5f00"
  },
  "category_id": {
    "$oid": "68e79f43b7afb57d706ea5f4"
  },
  "translations": {
    "name": {
      "en": "Fresh Basil",
      "fi": "Tuore basilika",
      "sv": "Färsk basilika"
    }
  },
  "created_at": {
    "$date": "2025-10-09T11:40:51.995Z"
  },
  "updated_at": {
    "$date": "2025-10-09T11:40:51.995Z"
  }
},
{
  "name": "Eggs",
  "allergen_tags": "[\"eggs\"]",
  "is_active": true,
  "restaurant_id": {
    "$oid": "68e79f43b7afb57d706ea5f00"
  },
  "category_id": {
    "$oid": "68c018a1699aa89005b47e1c"
  },
  "translations": {
    "name": {
      "en": "Eggs",
      "fi": "Kananmunat",
      "sv": "Ägg"
    }
  },
  "created_at": {
    "$date": "2025-10-09T11:40:51.995Z"
  },
  "updated_at": {
    "$date": "2025-10-09T11:40:51.995Z"
  }
},
{
  "name": "Butter",
  "allergen_tags": "[\"dairy\"]",
  "is_active": true,
  "restaurant_id": {
    "$oid": "68e79f43b7afb57d706ea5f00"
  },
  "category_id": {
    "$oid": "68c018a1699aa89005b47e1e"
  },
  "translations": {
    "name": {
      "en": "Butter",
      "fi": "Voi",
      "sv": "Smör"
    }
  },
  "created_at": {
    "$date": "2025-10-09T11:40:51.995Z"
  },
  "updated_at": {
    "$date": "2025-10-09T11:40:51.995Z"
  }
},
{
  "name": "Milk",
  "allergen_tags": "[\"dairy\"]",
  "is_active": true,
  "restaurant_id": {
    "$oid": "68e79f43b7afb57d706ea5f00"
  },
  "category_id": {
    "$oid": "68c018a1699aa89005b47e1e"
  },
  "translations": {
    "name": {
      "en": "Milk",
      "fi": "Maito",
      "sv": "Mjölk"
    }
  },
  "created_at": {
    "$date": "2025-10-09T11:40:51.995Z"
  },
  "updated_at": {
    "$date": "2025-10-09T11:40:51.995Z"
  }
},
{
  "name": "Heavy Cream",
  "allergen_tags": "[\"dairy\"]",
  "is_active": true,
  "restaurant_id": {
    "$oid": "68e79f43b7afb57d706ea5f00"
  },
  "category_id": {
    "$oid": "68c018a1699aa89005b47e1e"
  },
  "translations": {
    "name": {
      "en": "Heavy Cream",
      "fi": "Kuohukerma",
      "sv": "Vispgrädde"
    }
  },
  "created_at": {
    "$date": "2025-10-09T11:40:51.995Z"
  },
  "updated_at": {
    "$date": "2025-10-09T11:40:51.995Z"
  }
},
{
  "name": "Parmesan Cheese",
  "allergen_tags": "[\"dairy\"]",
  "is_active": true,
  "restaurant_id": {
    "$oid": "68e79f43b7afb57d706ea5f00"
  },
  "category_id": {
    "$oid": "68c018a1699aa89005b47e1e"
  },
  "translations": {
    "name": {
      "en": "Parmesan Cheese",
      "fi": "Parmesaanijuusto",
      "sv": "Parmesanost"
    }
  },
  "created_at": {
    "$date": "2025-10-09T11:40:51.995Z"
  },
  "updated_at": {
    "$date": "2025-10-09T11:40:51.995Z"
  }
},
{
  "name": "Shrimp",
  "allergen_tags": "[\"shellfish\"]",
  "is_active": true,
  "restaurant_id": {
    "$oid": "68e79f43b7afb57d706ea5f00"
  },
  "category_id": {
    "$oid": "68c018a1699aa89005b47e1c"
  },
  "translations": {
    "name": {
      "en": "Shrimp",
      "fi": "Katkarapu",
      "sv": "Räkor"
    }
  },
  "created_at": {
    "$date": "2025-10-09T11:40:51.995Z"
  },
  "updated_at": {
    "$date": "2025-10-09T11:40:51.995Z"
  }
},
{
  "name": "Tuna",
  "allergen_tags": "[\"fish\"]",
  "is_active": true,
  "restaurant_id": {
    "$oid": "68e79f43b7afb57d706ea5f00"
  },
  "category_id": {
    "$oid": "68c018a1699aa89005b47e1c"
  },
  "translations": {
    "name": {
      "en": "Tuna",
      "fi": "Tonnikala",
      "sv": "Tonfisk"
    }
  },
  "created_at": {
    "$date": "2025-10-09T11:40:51.995Z"
  },
  "updated_at": {
    "$date": "2025-10-09T11:40:51.995Z"
  }
},
{
  "name": "Cod",
  "allergen_tags": "[\"fish\"]",
  "is_active": true,
  "restaurant_id": {
    "$oid": "68e79f43b7afb57d706ea5f00"
  },
  "category_id": {
    "$oid": "68c018a1699aa89005b47e1c"
  },
  "translations": {
    "name": {
      "en": "Cod",
      "fi": "Turska",
      "sv": "Torsk"
    }
  },
  "created_at": {
    "$date": "2025-10-09T11:40:51.995Z"
  },
  "updated_at": {
    "$date": "2025-10-09T11:40:51.995Z"
  }
},
{
  "name": "Pork",
  "allergen_tags": "[]",
  "is_active": true,
  "restaurant_id": {
    "$oid": "68e79f43b7afb57d706ea5f00"
  },
  "category_id": {
    "$oid": "68c018a1699aa89005b47e1c"
  },
  "translations": {
    "name": {
      "en": "Pork",
      "fi": "Sianliha",
      "sv": "Fläsk"
    }
  },
  "created_at": {
    "$date": "2025-10-09T11:40:51.995Z"
  },
  "updated_at": {
    "$date": "2025-10-09T11:40:51.995Z"
  }
},
{
  "name": "Bacon",
  "allergen_tags": "[]",
  "is_active": true,
  "restaurant_id": {
    "$oid": "68e79f43b7afb57d706ea5f00"
  },
  "category_id": {
    "$oid": "68c018a1699aa89005b47e1c"
  },
  "translations": {
    "name": {
      "en": "Bacon",
      "fi": "Pekoni",
      "sv": "Bacon"
    }
  },
  "created_at": {
    "$date": "2025-10-09T11:40:51.995Z"
  },
  "updated_at": {
    "$date": "2025-10-09T11:40:51.995Z"
  }
},
{
  "name": "Cashews",
  "allergen_tags": "[\"nuts\"]",
  "is_active": true,
  "restaurant_id": {
    "$oid": "68e79f43b7afb57d706ea5f00"
  },
  "category_id": {
    "$oid": "68c018a1699aa89005b47e1d"
  },
  "translations": {
    "name": {
      "en": "Cashews",
      "fi": "Cashewpähkinät",
      "sv": "Cashewnötter"
    }
  },
  "created_at": {
    "$date": "2025-10-09T11:40:51.995Z"
  },
  "updated_at": {
    "$date": "2025-10-09T11:40:51.995Z"
  }
},
{
  "name": "Peanuts",
  "allergen_tags": "[\"nuts\"]",
  "is_active": true,
  "restaurant_id": {
    "$oid": "68e79f43b7afb57d706ea5f00"
  },
  "category_id": {
    "$oid": "68c018a1699aa89005b47e1d"
  },
  "translations": {
    "name": {
      "en": "Peanuts",
      "fi": "Maapähkinät",
      "sv": "Jordnötter"
    }
  },
  "created_at": {
    "$date": "2025-10-09T11:40:51.995Z"
  },
  "updated_at": {
    "$date": "2025-10-09T11:40:51.995Z"
  }
},
{
  "name": "Pine Nuts",
  "allergen_tags": "[\"nuts\"]",
  "is_active": true,
  "restaurant_id": {
    "$oid": "68e79f43b7afb57d706ea5f00"
  },
  "category_id": {
    "$oid": "68c018a1699aa89005b47e1d"
  },
  "translations": {
    "name": {
      "en": "Pine Nuts",
      "fi": "Männynsiemenet",
      "sv": "Pinjenötter"
    }
  },
  "created_at": {
    "$date": "2025-10-09T11:40:51.995Z"
  },
  "updated_at": {
    "$date": "2025-10-09T11:40:51.995Z"
  }
},
{
  "name": "Sesame Seeds",
  "allergen_tags": "[\"sesame\"]",
  "is_active": true,
  "restaurant_id": {
    "$oid": "68e79f43b7afb57d706ea5f00"
  },
  "category_id": {
    "$oid": "68c018a1699aa89005b47e1d"
  },
  "translations": {
    "name": {
      "en": "Sesame Seeds",
      "fi": "Seesaminsiemenet",
      "sv": "Sesamfrön"
    }
  },
  "created_at": {
    "$date": "2025-10-09T11:40:51.995Z"
  },
  "updated_at": {
    "$date": "2025-10-09T11:40:51.995Z"
  }
},
{
  "name": "Onion",
  "allergen_tags": "[]",
  "is_active": true,
  "restaurant_id": {
    "$oid": "68e79f43b7afb57d706ea5f00"
  },
  "category_id": {
    "$oid": "68c018a1699aa89005b47e20"
  },
  "translations": {
    "name": {
      "en": "Onion",
      "fi": "Sipuli",
      "sv": "Lök"
    }
  },
  "created_at": {
    "$date": "2025-10-09T11:40:51.995Z"
  },
  "updated_at": {
    "$date": "2025-10-09T11:40:51.995Z"
  }
},
{
  "name": "Garlic",
  "allergen_tags": "[]",
  "is_active": true,
  "restaurant_id": {
    "$oid": "68e79f43b7afb57d706ea5f00"
  },
  "category_id": {
    "$oid": "68c018a1699aa89005b47e20"
  },
  "translations": {
    "name": {
      "en": "Garlic",
      "fi": "Valkosipuli",
      "sv": "Vitlök"
    }
  },
  "created_at": {
    "$date": "2025-10-09T11:40:51.995Z"
  },
  "updated_at": {
    "$date": "2025-10-09T11:40:51.995Z"
  }
},
{
  "name": "Carrots",
  "allergen_tags": "[]",
  "is_active": true,
  "restaurant_id": {
    "$oid": "68e79f43b7afb57d706ea5f00"
  },
  "category_id": {
    "$oid": "68c018a1699aa89005b47e20"
  },
  "translations": {
    "name": {
      "en": "Carrots",
      "fi": "Porkkanat",
      "sv": "Morötter"
    }
  },
  "created_at": {
    "$date": "2025-10-09T11:40:51.995Z"
  },
  "updated_at": {
    "$date": "2025-10-09T11:40:51.995Z"
  }
},
{
  "name": "Broccoli",
  "allergen_tags": "[]",
  "is_active": true,
  "restaurant_id": {
    "$oid": "68e79f43b7afb57d706ea5f00"
  },
  "category_id": {
    "$oid": "68c018a1699aa89005b47e20"
  },
  "translations": {
    "name": {
      "en": "Broccoli",
      "fi": "Parsakaali",
      "sv": "Broccoli"
    }
  },
  "created_at": {
    "$date": "2025-10-09T11:40:51.995Z"
  },
  "updated_at": {
    "$date": "2025-10-09T11:40:51.995Z"
  }
},
{
  "name": "Mushrooms",
  "allergen_tags": "[]",
  "is_active": true,
  "restaurant_id": {
    "$oid": "68e79f43b7afb57d706ea5f00"
  },
  "category_id": {
    "$oid": "68c018a1699aa89005b47e20"
  },
  "translations": {
    "name": {
      "en": "Mushrooms",
      "fi": "Sienet",
      "sv": "Svamp"
    }
  },
  "created_at": {
    "$date": "2025-10-09T11:40:51.995Z"
  },
  "updated_at": {
    "$date": "2025-10-09T11:40:51.995Z"
  }
},
{
  "name": "Lettuce",
  "allergen_tags": "[]",
  "is_active": true,
  "restaurant_id": {
    "$oid": "68e79f43b7afb57d706ea5f00"
  },
  "category_id": {
    "$oid": "68c018a1699aa89005b47e20"
  },
  "translations": {
    "name": {
      "en": "Lettuce",
      "fi": "Lehtisalaatti",
      "sv": "Sallad"
    }
  },
  "created_at": {
    "$date": "2025-10-09T11:40:51.995Z"
  },
  "updated_at": {
    "$date": "2025-10-09T11:40:51.995Z"
  }
},
{
  "name": "Cucumber",
  "allergen_tags": "[]",
  "is_active": true,
  "restaurant_id": {
    "$oid": "68e79f43b7afb57d706ea5f00"
  },
  "category_id": {
    "$oid": "68c018a1699aa89005b47e20"
  },
  "translations": {
    "name": {
      "en": "Cucumber",
      "fi": "Kurkku",
      "sv": "Gurka"
    }
  },
  "created_at": {
    "$date": "2025-10-09T11:40:51.995Z"
  },
  "updated_at": {
    "$date": "2025-10-09T11:40:51.995Z"
  }
},
{
  "name": "Lemon",
  "allergen_tags": "[]",
  "is_active": true,
  "restaurant_id": {
    "$oid": "68e79f43b7afb57d706ea5f00"
  },
  "category_id": {
    "$oid": "68c018a1699aa89005b47e21"
  },
  "translations": {
    "name": {
      "en": "Lemon",
      "fi": "Sitruuna",
      "sv": "Citron"
    }
  },
  "created_at": {
    "$date": "2025-10-09T11:40:51.995Z"
  },
  "updated_at": {
    "$date": "2025-10-09T11:40:51.995Z"
  }
},
{
  "name": "Apple",
  "allergen_tags": "[]",
  "is_active": true,
  "restaurant_id": {
    "$oid": "68e79f43b7afb57d706ea5f00"
  },
  "category_id": {
    "$oid": "68c018a1699aa89005b47e21"
  },
  "translations": {
    "name": {
      "en": "Apple",
      "fi": "Omena",
      "sv": "Äpple"
    }
  },
  "created_at": {
    "$date": "2025-10-09T11:40:51.995Z"
  },
  "updated_at": {
    "$date": "2025-10-09T11:40:51.995Z"
  }
},
{
  "name": "Rice",
  "allergen_tags": "[]",
  "is_active": true,
  "restaurant_id": {
    "$oid": "68e79f43b7afb57d706ea5f00"
  },
  "category_id": {
    "$oid": "68c018a1699aa89005b47e22"
  },
  "translations": {
    "name": {
      "en": "Rice",
      "fi": "Riisi",
      "sv": "Ris"
    }
  },
  "created_at": {
    "$date": "2025-10-09T11:40:51.995Z"
  },
  "updated_at": {
    "$date": "2025-10-09T11:40:51.995Z"
  }
},
{
  "name": "Bread",
  "allergen_tags": "[\"gluten\"]",
  "is_active": true,
  "restaurant_id": {
    "$oid": "68e79f43b7afb57d706ea5f00"
  },
  "category_id": {
    "$oid": "68c018a1699aa89005b47e22"
  },
  "translations": {
    "name": {
      "en": "Bread",
      "fi": "Leipä",
      "sv": "Bröd"
    }
  },
  "created_at": {
    "$date": "2025-10-09T11:40:51.995Z"
  },
  "updated_at": {
    "$date": "2025-10-09T11:40:51.995Z"
  }
},
{
  "name": "Oats",
  "allergen_tags": "[\"gluten\"]",
  "is_active": true,
  "restaurant_id": {
    "$oid": "68e79f43b7afb57d706ea5f00"
  },
  "category_id": {
    "$oid": "68c018a1699aa89005b47e22"
  },
  "translations": {
    "name": {
      "en": "Oats",
      "fi": "Kaura",
      "sv": "Havre"
    }
  },
  "created_at": {
    "$date": "2025-10-09T11:40:51.995Z"
  },
  "updated_at": {
    "$date": "2025-10-09T11:40:51.995Z"
  }
},
{
  "name": "Olive Oil",
  "allergen_tags": "[]",
  "is_active": true,
  "restaurant_id": {
    "$oid": "68e79f43b7afb57d706ea5f00"
  },
  "category_id": {
    "$oid": "68c018a1699aa89005b47e1f"
  },
  "translations": {
    "name": {
      "en": "Olive Oil",
      "fi": "Oliiviöljy",
      "sv": "Olivolja"
    }
  },
  "created_at": {
    "$date": "2025-10-09T11:40:51.995Z"
  },
  "updated_at": {
    "$date": "2025-10-09T11:40:51.995Z"
  }
},
{
  "name": "Oregano",
  "allergen_tags": "[]",
  "is_active": true,
  "restaurant_id": {
    "$oid": "68e79f43b7afb57d706ea5f00"
  },
  "category_id": {
    "$oid": "68c018a1699aa89005b47e1f"
  },
  "translations": {
    "name": {
      "en": "Oregano",
      "fi": "Oregano",
      "sv": "Oregano"
    }
  },
  "created_at": {
    "$date": "2025-10-09T11:40:51.995Z"
  },
  "updated_at": {
    "$date": "2025-10-09T11:40:51.995Z"
  }
},
{
  "name": "Thyme",
  "allergen_tags": "[]",
  "is_active": true,
  "restaurant_id": {
    "$oid": "68e79f43b7afb57d706ea5f00"
  },
  "category_id": {
    "$oid": "68c018a1699aa89005b47e1f"
  },
  "translations": {
    "name": {
      "en": "Thyme",
      "fi": "Timjami",
      "sv": "Timjan"
    }
  },
  "created_at": {
    "$date": "2025-10-09T11:40:51.995Z"
  },
  "updated_at": {
    "$date": "2025-10-09T11:40:51.995Z"
  }
},
{
  "name": "Rosemary",
  "allergen_tags": "[]",
  "is_active": true,
  "restaurant_id": {
    "$oid": "68e79f43b7afb57d706ea5f00"
  },
  "category_id": {
    "$oid": "68c018a1699aa89005b47e1f"
  },
  "translations": {
    "name": {
      "en": "Rosemary",
      "fi": "Rosmariini",
      "sv": "Rosmarin"
    }
  },
  "created_at": {
    "$date": "2025-10-09T11:40:51.995Z"
  },
  "updated_at": {
    "$date": "2025-10-09T11:40:51.995Z"
  }
},
{
  "name": "Paprika",
  "allergen_tags": "[]",
  "is_active": true,
  "restaurant_id": {
    "$oid": "68e79f43b7afb57d706ea5f00"
  },
  "category_id": {
    "$oid": "68c018a1699aa89005b47e1f"
  },
  "translations": {
    "name": {
      "en": "Paprika",
      "fi": "Paprika",
      "sv": "Paprika"
    }
  },
  "created_at": {
    "$date": "2025-10-09T11:40:51.995Z"
  },
  "updated_at": {
    "$date": "2025-10-09T11:40:51.995Z"
  }
},
{
  "name": "Soy Sauce",
  "allergen_tags": "[\"soy\", \"gluten\"]",
  "is_active": true,
  "restaurant_id": {
    "$oid": "68e79f43b7afb57d706ea5f00"
  },
  "category_id": {
    "$oid": "68c018a1699aa89005b47e1f"
  },
  "translations": {
    "name": {
      "en": "Soy Sauce",
      "fi": "Soijakastike",
      "sv": "Sojasås"
    }
  },
  "created_at": {
    "$date": "2025-10-09T11:40:51.995Z"
  },
  "updated_at": {
    "$date": "2025-10-09T11:40:51.995Z"
  }
},
{
  "name": "Sugar",
  "allergen_tags": "[]",
  "is_active": true,
  "restaurant_id": {
    "$oid": "68e79f43b7afb57d706ea5f00"
  },
  "category_id": {
    "$oid": "68c018a1699aa89005b47e1f"
  },
  "translations": {
    "name": {
      "en": "Sugar",
      "fi": "Sokeri",
      "sv": "Socker"
    }
  },
  "created_at": {
    "$date": "2025-10-09T11:40:51.995Z"
  },
  "updated_at": {
    "$date": "2025-10-09T11:40:51.995Z"
  }
}]